{
    "title": "Warehouse - Midea Media",
    "label": "Warehouse",
    "filter": {
        "keyword": {
            "title": "Keyword",
            "placeholder": "Search Warehouse Name, Warehouse Code "
        },
        "is_using": {
            "title": "Status",
            "placeholder": "Select Status"
        },
        "is_agency": {
            "title": "Agency",
            "placeholder": "Select Status"
        }
    },
    "table": {
        "columns": {
            "code": "Code",
            "name": "Name",
            "note": "Note",
            "is_using": "Active",
            "is_agency": "Agency",
            "group_name": "Group"
        }
    },
    "form": {
        "code": {
            "title": "Code"
        },
        "name": {
            "title": "Name"
        },
        "name2": {
            "title": "Other Name"
        },
        "note": {
            "title": "Note"
        },
        "is_using": {
            "title": "Status"
        },
        "is_agency": {
            "title": "Agency"
        },
        "group_name": {
            "title": "Group "
        }
    }
}
